{"parent": "quest_giver:quest_0059_01", "reputation": 4, "icon": "minecraft:cod", "start": {"title": {"text": "Ты достал краснокаменную пыль? Я думаю, что мне нужен только 1."}, "description": {"text": "Ты достал краснокаменную пыль? Я думаю, что мне нужен только 1."}}, "complete": {"title": {"text": "Спасибо!"}, "description": {"text": "Спасибо! Вот за ваши проблемы."}}, "tasks": [{"item": {"item": "minecraft:redstone"}, "id": "quest_giver:gift", "times": 1}], "rewards": [{"command": "/advancement grant @p only custom:trade_fisherman", "id": "quest_giver:command"}, {"command": "/addreputation reputation:village @p 1", "id": "quest_giver:command"}, {"item": {"item": "minecraft:emerald"}, "id": "quest_giver:item", "times": 2}]}